{
  "accounts": [
    {
      "id": 1,
      "accountName": "IRA - 5200",
      "availableCash": 66607.65,
      "change": "0.34/55770"
    },
    {
      "id": 2,
      "accountName": "AAA - 1812",
      "availableCash": 92936.45,
      "change": "0.2/7174"
    },
    {
      "id": 3,
      "accountName": "AAA - 3810",
      "availableCash": 68856.33,
      "change": "1.6/61612"
    },
    {
      "id": 4,
      "accountName": "REG - 2019",
      "availableCash": 91938.77,
      "change": "2.3/99085"
    },
    {
      "id": 5,
      "accountName": "REG - 2025",
      "availableCash": 38736.44,
      "change": "3.1/28086"
    },
    {
      "id": 885,
      "accountName": "BBA - 3500",
      "availableCash": 98432.88,
      "change": "1.5/556"
    }
  ]
}
